{
    "filename": "listing_054.json",
    "text": "TITLE: Majestic 6-Bedroom Luxury Home With Modern Comfort and Historic Charm in Radziwie\nPROPERTY: house, 6 bedrooms, 3 bathrooms, 295 square meters\nLOCATION: Plock, Radziwie\nDESCRIPTION: Step into refined elegance with this spectacular 6-bedroom, 3-bathroom modern house, offering 295 sqm of beautifully curated living space. Expansive, sunlit interiors blend contemporary design with premium finishes, ensuring comfort and style. Entertain guests on the spacious terrace that seamlessly complements the chic living room, and store your belongings easily with the generous storage room. An underground garage provides secure parking for your vehicles, while dedicated space for children\u2019s recreation underscores the family-friendly ambiance. This residence is a masterpiece for discerning buyers seeking superior living.\nFEATURES: spacious 6 bedrooms, 3 modern bathrooms, children's playground area, ample storage room, sunlit terrace, private underground garage, premium finishes and fixtures, nearby shopping and dining options\nLIFESTYLE: perfect for young couples planning a family, close to vibrant social scene without sacrificing peace, safe neighborhood ambiance, historical character with modern comforts, exceptional commute possibilities\nNEIGHBORHOOD: Located in Radziwie\u2014one of Plock\u2019s most desirable medium-urban neighborhoods\u2014this residence situates you steps from historic landmarks while offering a unique sense of security and tranquility. With public transport and excellent highway access, the vibrant city center with premier shopping, dining, and cultural venues is effortlessly within reach. Pedestrian-friendly streets, leafy parks, and a distinct architectural charm define the neighborhood\u2019s inviting atmosphere.\nBUYER PROFILE: Designed for young couples who yearn for luxury, comfort, and playfulness in a prestigious, well-connected neighborhood\u2014a home ideal for growing families.\nMARKET POSITIONING: A premier luxury offering within Plock, uniquely blending neighborhood heritage with advanced amenities. Designed for upscale living, this property commands attention from sophisticated buyers who value both historic context and contemporary lifestyle ease.\n",
    "metadata": {
        "title": "Majestic 6-Bedroom Luxury Home With Modern Comfort and Historic Charm in Radziwie",
        "city": "Plock",
        "neighborhood": "Radziwie",
        "property_type": "house",
        "bedrooms": 6,
        "bathrooms": 3,
        "size_sqm": 295,
        "price": 1925000,
        "urban_level": "medium",
        "has_highway_access": true,
        "has_bike_lines_access": false,
        "has_public_transport_access": true,
        "has_airport_access": false
    },
    "embedding": [
        -0.005327381659299135,
        0.0309695266187191,
        0.0015865290770307183,
        0.03509240597486496,
        -0.030825704336166382,
        0.0036794289480894804,
        -0.03804074227809906,
        0.017342455685138702,
        0.002614252269268036,
        -0.046190615743398666,
        0.03863999620079994,
        -0.01990726962685585,
        0.0032779278699308634,
        -0.05757647380232811,
        0.054364461451768875,
        0.03286317363381386,
        -0.046334438025951385,
        -0.015089254826307297,
        0.00021498292335309088,
        0.0014472021721303463,
        0.004809025675058365,
        -0.0008419540245085955,
        -0.037705156952142715,
        -0.04480034485459328,
        0.005033746361732483,
        -0.030322330072522163,
        -0.01087648794054985,
        0.0024135017301887274,
        0.021561214700341225,
        -0.023766474798321724,
        -0.0195357296615839,
        -0.007934143766760826,
        0.04971424117684364,
        -0.03811265155673027,
        0.013914713636040688,
        -0.043458011001348495,
        -0.0013295982498675585,
        0.0071730888448655605,
        -0.0003548716485965997,
        -0.02255597896873951,
        0.007970098406076431,
        0.020027119666337967,
        -0.015316971577703953,
        0.022376202046871185,
        0.04341007024049759,
        0.0560423769056797,
        0.06750014424324036,
        -0.004236736800521612,
        0.03636282682418823,
        0.022975457832217216,
        0.00012715453340206295,
        0.01576041989028454,
        -0.032623469829559326,
        -0.023095307871699333,
        -0.023994192481040955,
        0.03216803818941116,
        -0.016611363738775253,
        0.004236736800521612,
        0.023850370198488235,
        0.053405653685331345,
        0.011925185099244118,
        -0.031736575067043304,
        -0.0021318516228348017,
        0.04384153336286545,
        0.0013580628437921405,
        -0.01812148652970791,
        -0.030034687370061874,
        0.026582974940538406,
        0.017953695729374886,
        -0.024090072140097618,
        0.04923483356833458,
        0.0005475697689689696,
        0.0016045067459344864,
        0.006268213037401438,
        -0.0003891415544785559,
        -0.020254837349057198,
        0.007095185574144125,
        -0.007934143766760826,
        -0.008940892294049263,
        0.023982206359505653,
        -0.00998958945274353,
        0.0021168701350688934,
        -0.028788236901164055,
        0.039622776210308075,
        -0.010546897538006306,
        -0.022208409383893013,
        0.0038172577042132616,
        -0.03986248001456261,
        0.024425655603408813,
        0.020170941948890686,
        0.0027760511729866266,
        0.00630416814237833,
        -0.002456947695463896,
        -0.006639751140028238,
        0.00416482612490654,
        -0.014346177689731121,
        -0.020578434690833092,
        0.04364977404475212,
        -0.006825520657002926,
        0.02689458802342415,
        0.009012803435325623,
        -0.052590664476156235,
        0.03509240597486496,
        0.008407555520534515,
        -0.014525954611599445,
        -0.00810193456709385,
        0.04041379317641258,
        0.02129754237830639,
        0.0656304657459259,
        -0.011050271801650524,
        -0.1187005341053009,
        0.04621458798646927,
        -0.019044341519474983,
        0.027733545750379562,
        -0.04343404248356819,
        0.034085653722286224,
        0.033941835165023804,
        -0.050673048943281174,
        -0.022867592051625252,
        0.054508283734321594,
        0.005411277525126934,
        0.020326748490333557,
        -0.0003393284569028765,
        -0.05345359444618225,
        0.014513969421386719,
        -0.04309845715761185,
        0.024281835183501244,
        -0.05776823312044144,
        -0.003967071883380413,
        -0.006052481010556221,
        -0.04556738957762718,
        0.0051086535677313805,
        -0.014489999040961266,
        0.009012803435325623,
        -0.01975146308541298,
        -0.008131898008286953,
        0.01975146308541298,
        0.011373870074748993,
        -0.07766351848840714,
        0.007101178169250488,
        0.018193397670984268,
        -0.006412034388631582,
        0.010864502750337124,
        -0.00212885532528162,
        -0.059014685451984406,
        0.03804074227809906,
        0.020230866968631744,
        0.0018442089203745127,
        -0.022963471710681915,
        0.06006937474012375,
        0.009336401708424091,
        0.0014629325596615672,
        -0.0030981511808931828,
        -0.027397962287068367,
        0.010780607350170612,
        -0.03509240597486496,
        0.05513150990009308,
        0.026702826842665672,
        -0.06476753950119019,
        0.0011078736279159784,
        -0.004074937663972378,
        -0.0005921393749304116,
        0.01116413064301014,
        0.009785843081772327,
        0.06845895200967789,
        0.03813662379980087,
        -0.00650791497901082,
        -0.0036854215431958437,
        -0.0730132982134819,
        0.0005651728715747595,
        0.048395875841379166,
        0.0010584350675344467,
        -0.008569354191422462,
        0.060932304710149765,
        0.006555855739861727,
        0.05048128589987755,
        -0.024785209447145462,
        -0.009606066159904003,
        0.0019056325545534492,
        -0.03938307240605354,
        0.009090706706047058,
        -0.03216803818941116,
        0.023562727496027946,
        0.010606822557747364,
        -0.009683969430625439,
        0.013111711479723454,
        -0.038064710795879364,
        0.013387368991971016,
        0.012656277045607567,
        0.059973493218421936,
        -0.03679428994655609,
        -0.006915409117937088,
        -0.03576356917619705,
        0.011511699296534061,
        0.020230866968631744,
        0.0018531976966187358,
        0.025456374511122704,
        0.020242851227521896,
        -0.017366426065564156,
        -0.0006078698206692934,
        -0.04808426275849342,
        -0.041684214025735855,
        0.017881784588098526,
        -0.06289786100387573,
        -0.0008719168254174292,
        0.026559004560112953,
        -0.04724530503153801,
        0.019931240007281303,
        -0.031592752784490585,
        -0.027589725330471992,
        0.029363520443439484,
        -0.042283471673727036,
        0.029315581545233727,
        0.004212766420096159,
        0.01945183426141739,
        -0.01333942823112011,
        -0.014765656553208828,
        0.01681511104106903,
        0.011056264862418175,
        0.04221155866980553,
        -0.01087648794054985,
        0.0036314886528998613,
        0.016467541456222534,
        0.017821859568357468,
        0.005390303675085306,
        0.0464303195476532,
        -0.000242885755142197,
        0.012704217806458473,
        0.009438274428248405,
        0.0045813084580004215,
        -0.025240642949938774,
        -0.006921401247382164,
        -0.015089254826307297,
        -0.05484386533498764,
        -0.015964167192578316,
        0.025456374511122704,
        0.019655581563711166,
        0.010013559833168983,
        0.036530617624521255,
        0.02440168522298336,
        -0.01564056985080242,
        0.001952074933797121,
        -0.014897492714226246,
        -0.017821859568357468,
        -0.004272691905498505,
        -0.04266699403524399,
        0.005920644849538803,
        -0.03377404063940048,
        0.010415061376988888,
        0.003991041798144579,
        0.002861445304006338,
        0.023838385939598083,
        -0.014358162879943848,
        -0.02514476142823696,
        0.005348355509340763,
        0.02859647385776043,
        -0.0011812824523076415,
        -0.0006659227074123919,
        -0.02802118845283985,
        -0.018325233832001686,
        0.010648771189153194,
        0.03703399375081062,
        -0.029747044667601585,
        -0.05431652069091797,
        0.012764142826199532,
        0.02557622641324997,
        -0.0026112559717148542,
        -0.013914713636040688,
        0.0383283831179142,
        -0.043889474123716354,
        -0.026367243379354477,
        -0.024281835183501244,
        -0.004236736800521612,
        0.022807665169239044,
        -0.0018516996642574668,
        0.024233894422650337,
        0.030945556238293648,
        0.0008442012476734817,
        0.01333942823112011,
        -0.01182930450886488,
        -0.01564056985080242,
        -0.035188283771276474,
        0.04837190732359886,
        -0.020830122753977776,
        -0.02986689656972885,
        0.030681883916258812,
        -0.012266760692000389,
        0.028188981115818024,
        -0.02809309959411621,
        -0.021273571997880936,
        -0.0020674315746873617,
        -0.06184317171573639,
        -0.017570171505212784,
        0.01305178552865982,
        -0.006639751140028238,
        -0.02269979938864708,
        0.008527406491339207,
        -0.08691602200269699,
        0.025983721017837524,
        -0.011517691425979137,
        0.06956158578395844,
        0.00892291497439146,
        0.012003088369965553,
        -0.03705796226859093,
        0.02122563123703003,
        0.03856808692216873,
        0.01592821255326271,
        -0.04667001962661743,
        -0.01812148652970791,
        0.015892256051301956,
        0.015604614280164242,
        -0.01039708312600851,
        0.0004734118701890111,
        -0.04702957347035408,
        -0.04015012085437775,
        -0.044344909489154816,
        -0.0021528254728764296,
        0.018097518011927605,
        0.007508671842515469,
        -0.058487340807914734,
        0.015664540231227875,
        0.011481735855340958,
        0.053261831402778625,
        -0.06505518406629562,
        -0.006723647005856037,
        -0.03772912919521332,
        -0.02145334891974926,
        -0.0030651921406388283,
        0.013255532830953598,
        -0.060117315500974655,
        0.041156869381666183,
        -0.03597930073738098,
        -0.014322207309305668,
        -0.021261585876345634,
        0.016012107953429222,
        -0.019643597304821014,
        0.005144608672708273,
        0.02404213137924671,
        -0.028860146179795265,
        0.011266004294157028,
        -0.0014277263544499874,
        -0.003439726773649454,
        -0.006801550276577473,
        -0.01976344734430313,
        0.007826277054846287,
        -0.031448930501937866,
        0.03161672130227089,
        -0.015269030816853046,
        0.018037591129541397,
        0.006400049198418856,
        -0.02514476142823696,
        0.03437329828739166,
        -0.01856493577361107,
        0.10566073656082153,
        0.02072225697338581,
        -0.05633002147078514,
        0.06385666877031326,
        0.007215036544948816,
        -0.08902540057897568,
        0.03152083978056908,
        0.0338938944041729,
        0.016048062592744827,
        -0.02351478673517704,
        0.03439726680517197,
        -0.012632306665182114,
        0.03923925384879112,
        -0.0397905670106411,
        0.012967890128493309,
        -0.04038982465863228,
        -0.0071251485496759415,
        0.0049348692409694195,
        -0.002891408046707511,
        0.0024749254807829857,
        0.041899945586919785,
        -0.010744651779532433,
        0.017234589904546738,
        0.04599885642528534,
        0.03161672130227089,
        0.004473442677408457,
        -0.0449681356549263,
        0.0165754072368145,
        -0.0009550635004416108,
        0.012764142826199532,
        -0.03701002150774002,
        0.044704463332891464,
        0.0073049250058829784,
        -0.00895287748426199,
        -0.024209924042224884,
        -0.07114361971616745,
        -0.0032090134918689728,
        0.02595975063741207,
        -0.03796882927417755,
        0.026582974940538406,
        0.03899955004453659,
        -0.010013559833168983,
        -0.008347629569470882,
        0.06740426272153854,
        0.027517814189195633,
        0.019427863880991936,
        -0.009558125399053097,
        -0.011637542396783829,
        -0.051344215869903564,
        -0.019859328866004944,
        -0.026822678744792938,
        -0.04113290086388588,
        0.018780669197440147,
        0.009857753291726112,
        -0.0018756698118522763,
        -0.011367877945303917,
        -0.03420550748705864,
        -0.011949155479669571,
        -0.018684787675738335,
        0.050097763538360596,
        0.03648267686367035,
        -0.0039011535700410604,
        -0.040965110063552856,
        -0.02343089133501053,
        0.022747740149497986,
        -0.00744275376200676,
        -0.033654190599918365,
        0.014418087899684906,
        -0.012668262235820293,
        -0.007466724142432213,
        -0.03164069354534149,
        -0.032239947468042374,
        0.03442123904824257,
        0.04341007024049759,
        -0.030418211594223976,
        -0.04918689280748367,
        -0.036003272980451584,
        -0.0028494601137936115,
        0.016851065680384636,
        -0.004542356822639704,
        -0.011859267018735409,
        -0.03104143775999546,
        0.014717715792357922,
        -0.021393422037363052,
        0.0038262465968728065,
        0.0065978034399449825,
        -0.04041379317641258,
        0.03449314832687378,
        -0.013651041314005852,
        -0.012596351094543934,
        0.016934961080551147,
        0.017929725348949432,
        0.013267518021166325,
        0.04472843185067177,
        0.03626694530248642,
        -0.053405653685331345,
        -0.011224056594073772,
        -0.015880271792411804,
        0.027973247691988945,
        -0.012332678772509098,
        0.02897999808192253,
        -0.046094734221696854,
        0.033510368317365646,
        0.016323721036314964,
        0.011601586826145649,
        -0.011715445667505264,
        -0.027925308793783188,
        0.05043334513902664,
        0.01651548221707344,
        0.0022352230735123158,
        0.01349523477256298,
        -0.033582281321287155,
        -0.08447106182575226,
        -0.032335828989744186,
        0.005486184265464544,
        0.0041318670846521854,
        -0.04667001962661743,
        0.036530617624521255,
        -0.04674193263053894,
        -0.008755123242735863,
        0.021657094359397888,
        -0.04233141243457794,
        -0.01754620298743248,
        -0.016107989475131035,
        0.022795680910348892,
        -0.001026974176056683,
        -0.004032989963889122,
        -0.016251809895038605,
        -0.003829242894425988,
        0.013734936714172363,
        0.017594141885638237,
        -0.04372168332338333,
        -0.03410962596535683,
        -0.03257553279399872,
        -0.0066637215204536915,
        -0.028716325759887695,
        0.019260073080658913,
        -0.04197185859084129,
        0.012194850482046604,
        0.03300699591636658,
        -0.010259254835546017,
        0.035787541419267654,
        -0.027757516130805016,
        -0.015161165036261082,
        0.03526019677519798,
        0.015952182933688164,
        0.01680312491953373,
        0.04120481014251709,
        -0.02026682160794735,
        -0.017306499183177948,
        0.03324669599533081,
        0.0010442028287798166,
        0.027230171486735344,
        -0.05206331983208656,
        -0.013627070933580399,
        -0.01153566874563694,
        0.005039738956838846,
        -0.011661512777209282,
        0.010870495811104774,
        -0.018229354172945023,
        -0.004152840934693813,
        0.041156869381666183,
        -0.0020764204673469067,
        -0.006909416522830725,
        0.01422632671892643,
        -0.044129177927970886,
        -0.03691413998603821,
        0.03789691999554634,
        0.01910426653921604,
        0.00423973286524415,
        0.002967813052237034,
        0.03530813753604889,
        -0.012320693582296371,
        -0.033798012882471085,
        -0.09914083778858185,
        0.010714689269661903,
        0.001194765674881637,
        0.020602405071258545,
        0.004946854431182146,
        -0.03363022208213806,
        0.042283471673727036,
        0.02866838499903679,
        0.013914713636040688,
        0.02624739333987236,
        -0.017438335344195366,
        -0.008251748979091644,
        -0.021021883934736252,
        0.03772912919521332,
        0.010271240025758743,
        0.005000787321478128,
        -0.005591053981333971,
        -0.040054239332675934,
        -0.007101178169250488,
        0.01337538380175829,
        0.022244365885853767,
        0.00048726965906098485,
        0.012548411265015602,
        0.0751706138253212,
        -0.02431778982281685,
        0.010630792938172817,
        -0.013986623845994473,
        -0.001473419601097703,
        0.027014439925551414,
        0.02742193266749382,
        0.029027938842773438,
        0.021249601617455482,
        0.036674439907073975,
        -0.05019364506006241,
        -0.011224056594073772,
        -0.014310222119092941,
        -0.01896044611930847,
        -0.005588057916611433,
        -0.01091244351118803,
        0.008683213032782078,
        0.04046173393726349,
        0.007358857896178961,
        0.02809309959411621,
        -0.007256984710693359,
        -0.0217529758810997,
        -0.020590420812368393,
        0.010427046567201614,
        0.041156869381666183,
        -0.0034636969212442636,
        -0.016131959855556488,
        -0.006945371627807617,
        0.02441367134451866,
        -0.0003612387226894498,
        -0.005788808688521385,
        0.0020015134941786528,
        0.003256953787058592,
        0.028212951496243477,
        0.004841984715312719,
        0.003523622639477253,
        0.050385404378175735,
        0.03065791353583336,
        0.05321389064192772,
        0.04815617576241493,
        -0.010624800808727741,
        0.003191035706549883,
        -0.00314309517852962,
        -0.0009722920949570835,
        0.006489937659353018,
        -0.010870495811104774,
        0.01896044611930847,
        0.014106475748121738,
        -0.023934265598654747,
        -0.004140855744481087,
        0.007502679247409105,
        -0.005387307144701481,
        -0.048995133489370346,
        0.01688702031970024,
        0.0007258482510223985,
        0.014777641743421555,
        -0.0007157358340919018,
        -0.034612998366355896,
        -0.007119155954569578,
        -0.0015273526078090072,
        -0.011254019103944302,
        -0.007250992115586996,
        -0.025839898735284805,
        -0.001394767314195633,
        -1.484093809267506e-05,
        0.03135304898023605,
        -0.004740111529827118,
        -0.02564813755452633,
        0.028836175799369812,
        -0.0006224766839295626,
        0.014657790772616863,
        -0.017342455685138702,
        0.03736957535147667,
        0.03605121374130249,
        0.017054812982678413,
        0.029579253867268562,
        -0.06673309952020645,
        -0.009186587296426296,
        -0.009570110589265823,
        0.016563422977924347,
        0.034013744443655014,
        -0.032767292112112045,
        0.014741686172783375,
        -0.037992801517248154,
        0.017869800329208374,
        0.027302082628011703,
        0.016455557197332382,
        0.011799341067671776,
        0.02301141247153282,
        0.001417988445609808,
        0.006489937659353018,
        0.019415879622101784,
        -0.009078721515834332,
        -0.002483914140611887,
        -0.010714689269661903,
        -0.016107989475131035,
        0.031089376658201218,
        0.038088683038949966,
        0.02785339765250683,
        0.009288460947573185,
        0.01990726962685585,
        0.014753671362996101,
        0.0276376660913229,
        -0.01924808695912361,
        -0.0028509581461548805,
        0.016539452597498894,
        0.05033746361732483,
        0.041612304747104645,
        0.03015453927218914,
        0.06289786100387573,
        -0.006957356818020344,
        0.01293193455785513,
        0.001014239969663322,
        -0.012512455694377422,
        0.005980570334941149,
        0.00822178553789854,
        -0.03902352228760719,
        -0.00676559517160058,
        -0.03813662379980087,
        0.02631930261850357,
        0.0714792013168335,
        0.03789691999554634,
        0.04933071509003639,
        0.021489303559064865,
        -0.02468932792544365,
        0.012979875318706036,
        0.04590297490358353,
        0.038376323878765106,
        -0.0442010872066021,
        0.002761069918051362,
        0.03943101316690445,
        0.019403893500566483,
        -0.036290913820266724,
        -0.011146153323352337,
        -0.012883993797004223,
        0.00634012371301651,
        0.0026936535723507404,
        0.02248406782746315,
        -0.006346116308122873,
        -0.006370086222887039,
        -0.0015775401843711734,
        0.040437765419483185,
        0.019272057339549065,
        0.0038741871248930693,
        0.058774981647729874,
        -0.021201660856604576,
        -0.03403771296143532,
        -0.010439031757414341,
        0.014993373304605484,
        -0.08653249591588974,
        0.026487095281481743,
        0.026726797223091125,
        -0.039167340844869614,
        -0.026918558403849602,
        0.013171636499464512,
        -0.04966630041599274,
        -0.004859962500631809,
        -0.047796621918678284,
        0.040965110063552856,
        -0.015209105797111988,
        0.014454043470323086,
        -0.0195357296615839,
        -0.044249027967453,
        -0.021465333178639412,
        -0.0018112498801201582,
        -0.00490490673109889,
        -0.003946097567677498,
        -0.006621773820370436,
        0.009162616916000843,
        -0.0063760788179934025,
        -0.027829427272081375,
        0.007346872705966234,
        0.012704217806458473,
        0.0005011274479329586,
        0.009240520186722279,
        0.00298579060472548,
        -0.01664731837809086,
        0.020242851227521896,
        -0.014322207309305668,
        0.0068375058472156525,
        0.028716325759887695,
        -0.00943228229880333,
        0.0021273570600897074,
        0.017558187246322632,
        0.042786844074726105,
        0.009899701923131943,
        -0.0034996522590517998,
        0.022735755890607834,
        -0.006741624791175127,
        -0.008077964186668396,
        0.019919253885746002,
        -0.03945498540997505,
        -0.058870863169431686,
        0.017306499183177948,
        0.013039800338447094,
        0.010361128486692905,
        0.033054936677217484,
        -0.028045158833265305,
        -0.04187597706913948,
        0.002539345296099782,
        -0.025480344891548157,
        0.008695198222994804,
        0.048036325722932816,
        0.0001114240731112659,
        -0.03871190920472145,
        -0.05685736611485481,
        0.010001574642956257,
        0.01028322521597147,
        0.004047971218824387,
        -0.0165754072368145,
        -0.0024135017301887274,
        -0.0021438365802168846,
        0.014010594226419926,
        -0.006657728925347328,
        -0.028692355379462242,
        0.031736575067043304,
        -0.018852578476071358,
        0.020482555031776428,
        -0.0003494408738333732,
        -0.007970098406076431,
        -0.00597158120945096,
        -0.001200009253807366,
        0.024078087881207466,
        -0.013567144982516766,
        0.01931999810039997,
        0.014094490557909012,
        0.027613695710897446,
        -0.02653503604233265,
        -0.03705796226859093,
        -0.022963471710681915,
        0.0457112118601799,
        0.000930344220250845,
        -0.02706238068640232,
        -0.006477952469140291,
        0.047868531197309494,
        0.01031918078660965,
        0.03782501071691513,
        -0.022064588963985443,
        0.02536049485206604,
        -0.01264429185539484,
        0.007934143766760826,
        0.002482416108250618,
        -0.0002335223980480805,
        0.0020254836417734623,
        -0.00047528455615974963,
        0.01725856028497219,
        0.013447294011712074,
        -0.04904307425022125,
        0.02785339765250683,
        0.01873272843658924,
        -0.012728187255561352,
        -0.017438335344195366,
        0.005165582522749901,
        0.04283478483557701,
        0.019871313124895096,
        0.0041768113151192665,
        -0.05867910385131836,
        0.03164069354534149,
        0.007233014330267906,
        -0.006873460952192545,
        -0.002605263376608491,
        0.013519205152988434,
        0.011649527586996555,
        0.00766447838395834,
        0.011295966804027557,
        0.00582176772877574,
        0.0228436216711998,
        0.001664432231336832,
        0.006681699305772781,
        -0.03665046766400337,
        -0.0039011535700410604,
        -0.03161672130227089,
        -0.02476123906672001,
        0.012584365904331207,
        0.011517691425979137,
        0.008653249591588974,
        -0.0291238185018301,
        -0.028356771916151047,
        0.04022203013300896,
        0.022244365885853767,
        0.0032090134918689728,
        -0.02115372009575367,
        -0.06471959501504898,
        0.007514664437621832,
        -0.007370843086391687,
        0.030130568891763687,
        0.021944737061858177,
        0.032263919711112976,
        0.013111711479723454,
        -0.020842107012867928,
        0.012560396455228329,
        -0.006184317171573639,
        -0.049426596611738205,
        -0.006933386437594891,
        0.019643597304821014,
        -0.010157381184399128,
        0.010678733699023724,
        -0.0038711908273398876,
        -0.017869800329208374,
        0.056569721549749374,
        -0.009648013859987259,
        -0.005905663128942251,
        0.061172004789114,
        -0.03871190920472145,
        -0.01577240601181984,
        -0.01194316241890192,
        0.022795680910348892,
        -0.0033528348430991173,
        -0.018912505358457565,
        0.024737268686294556,
        -0.014394118450582027,
        -0.011553646996617317,
        0.030490120872855186,
        -0.025600196793675423,
        -0.03669840842485428,
        0.0006670463480986655,
        0.025408435612916946,
        0.010810569860041142,
        0.02689458802342415,
        0.006603796035051346,
        -0.020746227353811264,
        -0.01577240601181984,
        -0.021117765456438065,
        0.014214341528713703,
        -0.0024764235131442547,
        -0.02153724431991577,
        -0.02365860901772976,
        0.014070520177483559,
        -0.014801612123847008,
        -0.027901338413357735,
        0.020182926207780838,
        0.013986623845994473,
        0.017222603783011436,
        -0.025696078315377235,
        0.019188161939382553,
        0.015736449509859085,
        -0.010768622159957886,
        0.0221245139837265,
        -0.019343968480825424,
        -0.035787541419267654,
        0.005615024361759424,
        -0.013627070933580399,
        -0.027373993769288063,
        0.003448715666308999,
        -0.03293508291244507,
        0.017654068768024445,
        0.0043535917066037655,
        0.022759724408388138,
        -0.0004730373329948634,
        -0.005594050511717796,
        -0.032335828989744186,
        0.026487095281481743,
        -0.011913199909031391,
        0.03089761547744274,
        0.00030599485035054386,
        -0.007952121086418629,
        -0.002398520242422819,
        -0.0044225058518350124,
        0.00018296021153219044,
        -0.022903546690940857,
        0.03485270217061043,
        -0.0010149891022592783,
        -0.004254714120179415,
        -0.005707908887416124,
        0.003197028301656246,
        0.00913864653557539,
        -0.02816501073539257,
        -0.017965681850910187,
        0.07032863050699234,
        0.041180841624736786,
        0.004311643540859222,
        0.050768930464982986,
        -0.00032247439958155155,
        0.003841228084638715,
        0.025528285652399063,
        -0.0165873933583498,
        0.003182046813890338,
        0.0014996370300650597,
        0.03300699591636658,
        -0.01120008621364832,
        -0.03868793696165085,
        0.005300415214151144,
        0.005438243970274925,
        0.00401800824329257,
        -0.0014397114282473922,
        0.002428482985123992,
        -0.01576041989028454,
        3.838980774162337e-05,
        0.0316886343061924,
        -0.0049768174067139626,
        0.0173304695636034,
        -0.03669840842485428,
        -0.0024794198106974363,
        -0.000808994984254241,
        0.02595975063741207,
        -0.019883299246430397,
        -0.004302654881030321,
        0.002220241818577051,
        0.041899945586919785,
        0.00338279758580029,
        0.014873522333800793,
        0.027757516130805016,
        0.001952074933797121,
        0.00017237960128113627,
        0.01952374540269375,
        0.003316879505291581,
        -0.030130568891763687,
        0.013135680928826332,
        0.022891562432050705,
        -0.00023764227807987481,
        -0.03502049297094345,
        -0.007916165515780449,
        -0.02735002338886261,
        -0.024713298305869102,
        -0.03801677003502846,
        -0.0033857938833534718,
        -0.000548318843357265,
        0.046046797186136246,
        -0.013519205152988434,
        -0.005869708023965359,
        -0.02794927917420864,
        -0.010103448294103146,
        -0.014058534987270832,
        0.012356649152934551,
        -0.014178385958075523,
        0.021645110100507736,
        0.02086607739329338,
        0.0008704186766408384,
        0.03413359448313713,
        -0.018145456910133362,
        0.018193397670984268,
        0.0390474908053875,
        0.05144009366631508,
        -0.004788051825016737,
        -0.015017343685030937,
        0.00788620300590992,
        0.02787736803293228,
        0.012027058750391006,
        -0.0191761776804924,
        -0.0324077382683754,
        0.009923671372234821,
        0.03420550748705864,
        -0.030466152355074883,
        0.007376835681498051,
        -0.011595594696700573,
        -0.004913895390927792,
        -0.029219700023531914,
        -0.005141612607985735,
        -0.025456374511122704,
        0.02211252972483635,
        -0.021932752802968025,
        -0.04180406779050827,
        0.016323721036314964,
        -0.008179837837815285,
        -0.014370148070156574,
        0.02483315020799637,
        -0.00010627422307152301,
        0.008994825184345245,
        0.0011011320166289806,
        -0.033869922161102295,
        0.01709076762199402,
        0.04101305082440376,
        0.021776946261525154,
        -0.0008651751559227705,
        0.00034082657657563686,
        -0.015185135416686535,
        -0.006214280147105455,
        -0.03444520756602287,
        -0.014981388114392757,
        -0.005522139836102724,
        0.019739476963877678,
        0.012560396455228329,
        0.02263987436890602,
        -0.002677174052223563,
        0.0165754072368145,
        0.0021767958533018827,
        0.02993880584836006,
        -0.020099030807614326,
        0.007724403869360685,
        -0.010540904477238655,
        -0.001776792691089213,
        0.024713298305869102,
        -0.032239947468042374,
        -0.011529676616191864,
        0.00961805135011673,
        0.009186587296426296,
        0.002966315019875765,
        -0.012392604723572731,
        -0.030250418931245804,
        0.011403832584619522,
        -0.012764142826199532,
        0.015209105797111988,
        0.018157443031668663,
        -0.009252505376935005,
        -0.0283807422965765,
        -0.007358857896178961,
        -0.009006810374557972,
        -0.0037872949615120888,
        0.02823692001402378,
        -0.0022277324460446835,
        0.03492461144924164,
        -0.03986248001456261,
        -0.0061963023617863655,
        0.030849674716591835,
        0.010780607350170612,
        -0.009426289238035679,
        -0.01643158681690693,
        -0.014046549797058105,
        -0.019200148060917854,
        0.021069824695587158,
        -0.003775309771299362,
        0.009222542867064476,
        0.018397144973278046,
        -0.012656277045607567,
        0.03739354386925697,
        0.016347691416740417,
        0.00936037115752697,
        -0.01264429185539484,
        0.002696649869903922,
        0.014573894441127777,
        0.012848039157688618,
        0.002492903033271432,
        0.013147666119039059,
        -0.023994192481040955,
        0.019427863880991936,
        0.0010651766788214445,
        -0.01242856029421091,
        0.005174571648240089,
        0.018445085734128952,
        0.06179523095488548,
        -0.01397463958710432,
        0.016863049939274788,
        -0.027661636471748352,
        0.020830122753977776,
        -0.007197059225291014,
        0.00045168885844759643,
        0.005423262715339661,
        0.012308708392083645,
        0.002620244864374399,
        -0.02011101506650448,
        0.0026277354918420315,
        -0.009546141140162945,
        0.008827034384012222,
        -0.0053303781896829605,
        0.009048759005963802,
        -0.017006872221827507,
        0.019559700042009354,
        0.012344663962721825,
        -0.025456374511122704,
        0.004853969905525446,
        0.013854787684977055,
        -0.010205321945250034,
        0.01488550752401352,
        0.0012157396413385868,
        -0.011667504906654358,
        -0.03693811222910881,
        -0.0014636816922575235,
        -0.0025902821216732264,
        -0.029651163145899773,
        0.024281835183501244,
        -0.02845265343785286,
        0.0038472204469144344,
        0.014238311909139156,
        -0.02292751707136631,
        0.0010486971586942673,
        0.03250361979007721,
        -0.03286317363381386,
        0.030178509652614594,
        0.019727492704987526,
        -0.0006063716718927026,
        -0.04144451394677162,
        -0.04563930258154869,
        -0.003104143775999546,
        0.008593324571847916,
        0.0010599332163110375,
        0.007694440893828869,
        0.006298175547271967,
        -0.009929664433002472,
        0.02986689656972885,
        0.05978173390030861,
        -0.04801235347986221,
        0.010744651779532433,
        -0.019931240007281303,
        -0.015233076177537441,
        -0.019511761143803596,
        -0.007544627413153648,
        0.007772344164550304,
        0.018972430378198624,
        -0.020099030807614326,
        0.0324077382683754,
        0.03437329828739166,
        0.017606128007173538,
        0.005782816093415022,
        0.008437518030405045,
        -0.009827790781855583,
        -0.02866838499903679,
        0.03303096443414688,
        0.08720366656780243,
        0.02603165991604328,
        8.174220420187339e-05,
        0.027302082628011703,
        -0.017222603783011436,
        -0.0012854031519964337,
        -0.023167219012975693,
        0.022663844749331474,
        0.00383223919197917,
        0.0019745470490306616,
        -0.02019491232931614,
        0.00877310149371624,
        0.0025767988990992308,
        -0.04216361790895462,
        -0.0009700449299998581,
        -0.04961835965514183,
        -0.03813662379980087,
        -0.006519900169223547,
        0.03703399375081062,
        -0.02335898019373417,
        0.04000629857182503,
        0.020698286592960358,
        0.015820346772670746,
        0.021405408158898354,
        -0.020590420812368393,
        -0.02086607739329338,
        -0.022472083568572998,
        -0.031664662063121796,
        -0.02086607739329338,
        0.023574713617563248,
        0.02307133749127388,
        0.006939379032701254,
        0.011056264862418175,
        -0.02572004683315754,
        0.02181290090084076,
        0.016323721036314964,
        -0.020949972793459892,
        -0.020099030807614326,
        -0.00634012371301651,
        -0.010666748508810997,
        0.00025580721558071673,
        0.0257919579744339,
        -0.053932998329401016,
        0.02278369478881359,
        0.0206383615732193,
        0.020314762368798256,
        -0.04614267498254776,
        0.0044195097871124744,
        -0.003319875570014119,
        -0.01813347265124321,
        0.06740426272153854,
        0.017558187246322632,
        0.01812148652970791,
        0.018744712695479393,
        0.0435059517621994,
        -0.03125716745853424,
        0.026271361857652664,
        0.005033746361732483,
        -0.02639121375977993,
        0.01440610270947218,
        -0.01923610270023346,
        0.038807787001132965,
        -0.02263987436890602,
        -0.011685483157634735,
        0.020686300471425056,
        -0.04261905327439308,
        -0.017881784588098526,
        0.03118525817990303,
        -0.04187597706913948,
        -0.004365576431155205,
        0.010576860047876835,
        0.016767170280218124,
        0.004233740270137787,
        0.0035326112993061543,
        -0.007376835681498051,
        -0.011817319318652153,
        0.053549475967884064,
        0.02919572964310646,
        -0.002862943336367607,
        -0.011727430857717991,
        -0.0070172823034226894,
        0.008185830898582935,
        -0.004281681030988693,
        0.052974190562963486,
        -0.019068311899900436,
        -0.009456252679228783,
        0.02277171052992344,
        0.02735002338886261,
        -0.015544688329100609,
        0.009797828271985054,
        -0.027997218072414398,
        0.02232826128602028,
        -0.02373052015900612,
        -0.008317667059600353,
        -0.007233014330267906,
        0.027685604989528656,
        0.004206773824989796,
        0.005612028297036886,
        -0.0011213569669052958,
        0.025456374511122704,
        -0.0059116557240486145,
        -0.003104143775999546,
        -0.007316910196095705,
        0.03303096443414688,
        -0.013543175533413887,
        0.04599885642528534,
        0.019811388105154037,
        -0.0074187833815813065,
        0.020254837349057198,
        -0.0006048735813237727,
        -0.029027938842773438,
        -0.01614394411444664,
        0.04305051639676094,
        -0.01031918078660965,
        -0.04465652257204056,
        -0.00851542130112648,
        -0.013435308821499348,
        -0.052159201353788376,
        0.005141612607985735,
        -0.027469873428344727,
        0.014681760221719742,
        -0.017809875309467316,
        0.013591115362942219,
        0.0004015012236777693,
        -0.0009902698220685124,
        -0.039838507771492004,
        0.017438335344195366,
        0.034541089087724686,
        -0.021800916641950607,
        0.0034726858139038086,
        -0.0034726858139038086,
        0.02071027085185051,
        -0.003991041798144579,
        -0.01731848530471325,
        -0.02198069356381893,
        -0.0036704400554299355,
        -0.0018172424752265215,
        -0.015436822548508644,
        0.003460700623691082,
        -0.008623287081718445,
        -0.017881784588098526,
        0.00048502246499992907,
        -0.000350939022609964,
        -0.02720620110630989,
        -0.01578439027070999,
        -0.003457704558968544,
        0.010301202535629272,
        -0.032695382833480835,
        -0.00580378994345665,
        0.008563362061977386,
        -0.03602724149823189,
        -0.01828927919268608,
        -0.03530813753604889,
        -0.0515839159488678,
        0.018828608095645905,
        0.03943101316690445,
        0.004973820876330137,
        0.0016569416038691998,
        -0.025744017213582993,
        -0.025384465232491493,
        -0.0152930011972785,
        -0.02123761549592018,
        -0.01674319989979267,
        -0.01349523477256298,
        -0.01091244351118803,
        0.01790575496852398,
        0.03739354386925697,
        -0.018708758056163788,
        0.03310287743806839,
        -0.007760359439998865,
        0.020842107012867928,
        0.01065476331859827,
        0.003319875570014119,
        0.026798708364367485,
        -0.013447294011712074,
        -0.004024000838398933,
        0.011787356808781624,
        0.015221090987324715,
        -0.0012389607727527618,
        0.0032239947468042374,
        -0.00888695940375328,
        -0.008856996893882751,
        -0.016719229519367218,
        -0.006531885359436274,
        0.02845265343785286,
        0.006861475761979818,
        0.027230171486735344,
        -0.019296027719974518,
        0.0317126028239727,
        0.004032989963889122,
        0.0013153658946976066,
        0.00782028492540121,
        0.007089192979037762,
        0.02189679816365242,
        0.0030082627199590206,
        -0.036314886063337326,
        -0.024641387164592743,
        -0.009612059220671654,
        0.009372356347739697,
        0.017234589904546738,
        -0.02254399284720421,
        -0.02153724431991577,
        -0.005243485793471336,
        0.008119912818074226,
        -0.006244242656975985,
        -0.009815805591642857,
        0.019188161939382553,
        0.028620444238185883,
        -0.013663026504218578,
        0.008934900164604187,
        -0.02514476142823696,
        -0.04003027081489563,
        -0.005318392999470234,
        0.015964167192578316,
        -0.0030831696931272745,
        0.0022621897514909506,
        0.00325395748950541,
        0.010864502750337124,
        -0.02639121375977993,
        0.0032329836394637823,
        -0.010121425613760948,
        -0.0036434736102819443,
        -0.009917679242789745,
        -0.004641233943402767,
        -0.006298175547271967,
        0.032479651272296906,
        -0.007832270115613937,
        0.02277171052992344,
        -0.004281681030988693,
        -0.017582157626748085,
        0.016024092212319374,
        -0.001794770359992981,
        0.03650664910674095,
        -0.03427741676568985,
        0.009264490567147732,
        -0.012536426074802876,
        0.02269979938864708,
        0.006250235252082348,
        0.004509397782385349,
        0.024593446403741837,
        -0.007958113215863705,
        -0.03111334703862667,
        0.030394241213798523,
        -0.03197627514600754,
        0.024809179827570915,
        -0.024138012900948524,
        0.01544880773872137,
        -0.00744275376200676,
        -0.03736957535147667,
        0.017570171505212784,
        -0.03509240597486496,
        0.04436888173222542,
        0.015904242172837257,
        -0.04508798569440842,
        -0.010331165045499802,
        0.03185642510652542,
        -0.027661636471748352,
        0.008269726298749447,
        0.0177020076662302,
        0.005096668377518654,
        -0.02720620110630989,
        -0.05182361975312233,
        0.017486276105046272,
        0.01798965036869049,
        0.00019737979164347053,
        -0.02159716933965683,
        -0.02490505948662758,
        -0.008916922844946384,
        -0.021021883934736252,
        -0.04266699403524399,
        -0.03377404063940048,
        -0.019331984221935272,
        0.0006925147026777267,
        -0.01415441557765007,
        -0.013591115362942219,
        0.03221597895026207,
        -4.417168747750111e-05,
        -0.023862356320023537,
        0.016215855255723,
        -0.0044045280665159225,
        -0.026271361857652664,
        0.008695198222994804,
        -0.018313249573111534,
        -0.016863049939274788,
        -0.0008397068013437092,
        -0.009258498437702656,
        0.004722133744508028,
        0.03899955004453659,
        0.016527468338608742,
        -0.00201799301430583,
        -0.026175482198596,
        -0.009444267489016056,
        -0.020973943173885345,
        0.013327443040907383,
        0.04877940192818642,
        0.0052195158787071705,
        -0.007005297113209963,
        0.002447958802804351,
        -0.017150692641735077,
        -0.005384311079978943,
        0.01910426653921604,
        -0.03197627514600754,
        -0.020949972793459892,
        -0.00273560150526464,
        0.011901214718818665,
        0.036003272980451584,
        0.015508733689785004,
        0.03780103847384453,
        -0.0024149997625499964,
        0.007197059225291014,
        -0.013219577260315418,
        -0.003991041798144579,
        -0.00222173985093832,
        -0.004958839621394873,
        -0.006741624791175127,
        0.027158260345458984,
        0.026822678744792938,
        0.0029408466070890427,
        -0.00251387688331306,
        0.06606192886829376,
        -0.008215793408453465,
        0.008018039166927338,
        0.02490505948662758,
        -0.00403598602861166,
        0.008251748979091644,
        -0.013555159792304039,
        0.0007501930231228471,
        -0.0077064260840415955,
        0.002426984952762723,
        0.02255597896873951,
        -0.010606822557747364,
        0.01961962692439556,
        -0.00610042130574584,
        -0.013459279201924801,
        0.03842426463961601,
        -0.023622652515769005,
        -0.04048570245504379,
        -0.001162555767223239,
        0.01050494983792305,
        -0.013591115362942219,
        0.012632306665182114,
        -0.003982053138315678,
        0.027302082628011703,
        -0.009701946750283241,
        0.002798523288220167,
        0.03655458614230156,
        -0.014178385958075523,
        -0.03264744207262993,
        0.03523622453212738,
        -0.014034564606845379,
        -0.00580378994345665,
        0.02675076760351658,
        -0.009564118459820747,
        -0.0034457193687558174,
        0.025456374511122704,
        0.025024911388754845,
        -0.0028419694863259792,
        -0.025240642949938774,
        -0.01665930449962616,
        0.021908782422542572,
        -0.007227021735161543,
        -0.01312369666993618,
        -0.000639330770354718,
        -0.0034427230712026358,
        -0.001896643778309226,
        -0.003580551827326417,
        -0.02299942821264267,
        0.005102660972625017,
        0.04319433867931366,
        -0.0008194819674827158,
        0.039838507771492004,
        0.012152901850640774,
        -0.0094023197889328,
        -0.020674316212534904,
        -0.04321831092238426,
        -0.001510872971266508,
        -0.007988076657056808,
        -0.03286317363381386,
        -0.009414304047822952,
        -0.007310917600989342,
        0.007119155954569578,
        -0.020842107012867928,
        -0.01286002341657877,
        0.010744651779532433,
        -0.01371096633374691,
        0.01381883304566145,
        0.011475743725895882,
        0.01220683567225933,
        -0.015676524490118027
    ]
}